[{"__type__":"cc.SpriteFrame","content":{"name":"l_jishen","texture":"1f5449040","rect":[3,636,121,145],"offset":[0,0],"originalSize":[121,145],"capInsets":[0,0,0,0]}},{"__type__":"cc.SpriteFrame","content":{"name":"l_bo","texture":"1f5449040","rect":[962,49,58,68],"offset":[0,-0.5],"originalSize":[60,69],"capInsets":[0,0,0,0]}},[{"__type__":"cc.Prefab","_name":"PbWingman_BLUEBALL","data":{"__id__":1}},{"__type__":"cc.Node","_name":"PbWingman_BLUE_BALL","_children":[{"__id__":2},{"__id__":3},{"__id__":10}],"_level":1,"_components":[{"__type__":"d9e67Ba8zlMf4UWcTUEMeih","node":{"__id__":1},"ndBulletLeft":{"__id__":5},"ndBulletRight":{"__id__":8},"ndBullet":{"__id__":10}}],"_prefab":{"__type__":"cc.PrefabInfo","root":{"__id__":1},"asset":{"__uuid__":"3bBeRdkWdIfbDWpVdQeMek"},"fileId":"48Ib74nZxK6IAfhpeaiAzc"},"_scale":{"__type__":"cc.Vec3","x":1,"y":1,"z":1}},{"__type__":"cc.Node","_name":"fuselage2","_parent":{"__id__":1},"_level":7,"_components":[{"__type__":"cc.Sprite","node":{"__id__":2},"_spriteFrame":{"__uuid__":"01P0a5OBhBbZbpMlyI877Y"}}],"_prefab":{"__type__":"cc.PrefabInfo","root":{"__id__":1},"asset":{"__uuid__":"3bBeRdkWdIfbDWpVdQeMek"},"fileId":"b3AgV3KiNGLKXbItyLJCSt"},"_contentSize":{"__type__":"cc.Size","width":121,"height":145},"_scale":{"__type__":"cc.Vec3","x":1,"y":1,"z":1}},{"__type__":"cc.Node","_name":"wingman","_parent":{"__id__":1},"_children":[{"__id__":4},{"__id__":7}],"_level":7,"_prefab":{"__type__":"cc.PrefabInfo","root":{"__id__":1},"asset":{"__uuid__":"3bBeRdkWdIfbDWpVdQeMek"},"fileId":"2bjsFn08dIH7GKPnemvtBJ"},"_scale":{"__type__":"cc.Vec3","x":1,"y":1,"z":1}},{"__type__":"cc.Node","_name":"yi","_parent":{"__id__":3},"_children":[{"__id__":5},{"__id__":6}],"_level":5,"_components":[{"__type__":"cc.Sprite","node":{"__id__":4},"_spriteFrame":{"__uuid__":"f3K2M/755PPI0xbnNEQTbh"}}],"_prefab":{"__type__":"cc.PrefabInfo","root":{"__id__":1},"asset":{"__uuid__":"3bBeRdkWdIfbDWpVdQeMek"},"fileId":"b1+XXMsN5IH4WkkgqNS3E1"},"_contentSize":{"__type__":"cc.Size","width":71,"height":127},"_position":{"__type__":"cc.Vec3","x":-80,"y":30},"_scale":{"__type__":"cc.Vec3","x":1,"y":1,"z":1}},{"__type__":"cc.Node","_name":"pan2","_parent":{"__id__":4},"_level":6,"_components":[{"__type__":"cc.Sprite","node":{"__id__":5},"_spriteFrame":{"__uuid__":"31qwP+aF5FjKD3WK9oDxpy"}},{"__type__":"cc.Animation","node":{"__id__":5},"_defaultClip":{"__uuid__":"2eHEJ9V+FI3bWQMgN8GIEW"},"_clips":[{"__uuid__":"2eHEJ9V+FI3bWQMgN8GIEW"}],"playOnLoad":true}],"_prefab":{"__type__":"cc.PrefabInfo","root":{"__id__":1},"asset":{"__uuid__":"3bBeRdkWdIfbDWpVdQeMek"},"fileId":"c7MJ94oM1BKJgodZ+sHIfA"},"_contentSize":{"__type__":"cc.Size","width":60,"height":69},"_anchorPoint":{"__type__":"cc.Vec2","x":0.5},"_position":{"__type__":"cc.Vec3","y":61.9},"_scale":{"__type__":"cc.Vec3","x":1,"y":1,"z":1}},{"__type__":"cc.Node","_name":"yi2","_parent":{"__id__":4},"_level":6,"_components":[{"__type__":"cc.Sprite","node":{"__id__":6},"_spriteFrame":{"__uuid__":"f0c9Pj41ZBWY5VhXwddBr0"}},{"__type__":"cc.Animation","node":{"__id__":6},"_defaultClip":{"__uuid__":"edmCMpHE5GFYfYCcBI0jeo"},"_clips":[{"__uuid__":"edmCMpHE5GFYfYCcBI0jeo"}],"playOnLoad":true}],"_prefab":{"__type__":"cc.PrefabInfo","root":{"__id__":1},"asset":{"__uuid__":"3bBeRdkWdIfbDWpVdQeMek"},"fileId":"f5NzqKaXNO6b3q6JlZg9Z8"},"_contentSize":{"__type__":"cc.Size","width":29,"height":29},"_position":{"__type__":"cc.Vec3","y":-30},"_scale":{"__type__":"cc.Vec3","x":1,"y":1,"z":1}},{"__type__":"cc.Node","_name":"yi","_parent":{"__id__":3},"_children":[{"__id__":8},{"__id__":9}],"_level":5,"_components":[{"__type__":"cc.Sprite","node":{"__id__":7},"_spriteFrame":{"__uuid__":"f3K2M/755PPI0xbnNEQTbh"}}],"_prefab":{"__type__":"cc.PrefabInfo","root":{"__id__":1},"asset":{"__uuid__":"3bBeRdkWdIfbDWpVdQeMek"},"fileId":"729Uv8aN1Bj5QG13D8BaSV"},"_contentSize":{"__type__":"cc.Size","width":71,"height":127},"_position":{"__type__":"cc.Vec3","x":80,"y":30},"_scale":{"__type__":"cc.Vec3","x":-1,"y":1,"z":1}},{"__type__":"cc.Node","_name":"pan2","_parent":{"__id__":7},"_level":6,"_components":[{"__type__":"cc.Sprite","node":{"__id__":8},"_spriteFrame":{"__uuid__":"31qwP+aF5FjKD3WK9oDxpy"}},{"__type__":"cc.Animation","node":{"__id__":8},"_defaultClip":{"__uuid__":"2eHEJ9V+FI3bWQMgN8GIEW"},"_clips":[{"__uuid__":"2eHEJ9V+FI3bWQMgN8GIEW"}],"playOnLoad":true}],"_prefab":{"__type__":"cc.PrefabInfo","root":{"__id__":1},"asset":{"__uuid__":"3bBeRdkWdIfbDWpVdQeMek"},"fileId":"b9m/2rabZO4ZUKxKRbXfsJ"},"_contentSize":{"__type__":"cc.Size","width":60,"height":69},"_anchorPoint":{"__type__":"cc.Vec2","x":0.5},"_position":{"__type__":"cc.Vec3","y":61.9},"_scale":{"__type__":"cc.Vec3","x":-1,"y":1,"z":1}},{"__type__":"cc.Node","_name":"yi2","_parent":{"__id__":7},"_level":6,"_components":[{"__type__":"cc.Sprite","node":{"__id__":9},"_spriteFrame":{"__uuid__":"f0c9Pj41ZBWY5VhXwddBr0"}},{"__type__":"cc.Animation","node":{"__id__":9},"_defaultClip":{"__uuid__":"edmCMpHE5GFYfYCcBI0jeo"},"_clips":[{"__uuid__":"edmCMpHE5GFYfYCcBI0jeo"}],"playOnLoad":true}],"_prefab":{"__type__":"cc.PrefabInfo","root":{"__id__":1},"asset":{"__uuid__":"3bBeRdkWdIfbDWpVdQeMek"},"fileId":"9fzoxiIfdL84KCjrW905lz"},"_contentSize":{"__type__":"cc.Size","width":29,"height":29},"_position":{"__type__":"cc.Vec3","y":-30},"_scale":{"__type__":"cc.Vec3","x":-1,"y":1,"z":1}},{"__type__":"cc.Node","_name":"pan2","_parent":{"__id__":1},"_active":false,"_level":2,"_components":[{"__type__":"cc.Sprite","node":{"__id__":10},"_spriteFrame":{"__uuid__":"6459KgRx5OaaVdvnbOuHM/"}}],"_prefab":{"__type__":"cc.PrefabInfo","root":{"__id__":1},"asset":{"__uuid__":"3bBeRdkWdIfbDWpVdQeMek"},"fileId":"b0UXs9MIJLq7aLLA1f0Dfv"},"_contentSize":{"__type__":"cc.Size","width":547,"height":244},"_scale":{"__type__":"cc.Vec3","x":0.2,"y":0.2,"z":1}}],{"__type__":"cc.SpriteFrame","content":{"name":"l_bo1","texture":"166f5ef2c","rect":[643,3,547,244],"offset":[0,0],"originalSize":[551,244],"rotated":1,"capInsets":[0,0,0,0]}},{"__type__":"cc.SpriteFrame","content":{"name":"l_shan","texture":"1f5449040","rect":[729,3,29,29],"offset":[0,0],"originalSize":[31,31],"capInsets":[0,0,0,0]}},{"__type__":"cc.SpriteFrame","content":{"name":"l_jiyi","texture":"1b1c5656a","rect":[311,950,71,127],"offset":[0,0],"originalSize":[71,127],"rotated":1,"capInsets":[0,0,0,0]}}]